arrowcm/__about__.py
arrowcm/__init__.py
arrowcm-0.0.2.dist-info/METADATA
arrowcm-0.0.2.dist-info/WHEEL
arrowcm-0.0.2.dist-info/licenses/LICENSE
arrowcm-0.0.2.dist-info/RECORD
