Metadata-Version: 2.1
Name: arrowcm
Version: 0.0.2
Project-URL: Documentation, https://github.com/jsurloppe/arrowcm#readme
Project-URL: Issues, https://github.com/jsurloppe/arrowcm/issues
Project-URL: Source, https://github.com/jsurloppe/arrowcm
Author-email: Julien Surloppe <julien@surloppe.fr>
License-Expression: GPL-3.0-or-later
License-File: LICENSE
Classifier: Development Status :: 4 - Beta
Classifier: Programming Language :: Python
Classifier: Programming Language :: Python :: 3.7
Classifier: Programming Language :: Python :: 3.8
Classifier: Programming Language :: Python :: 3.9
Classifier: Programming Language :: Python :: 3.10
Classifier: Programming Language :: Python :: 3.11
Classifier: Programming Language :: Python :: Implementation :: CPython
Requires-Python: >=3.7
Requires-Dist: jupyter-server
Requires-Dist: pyarrow
